autogonai/__init__.py
autogonai/connector.py
autogonai/constants.py
autogonai/errors.py
autogonai/core/__init__.py
autogonai/core/api.py
autogonai/core/qore.py
autogonai/development/__init__.py
autogonai/development/auto_deep_learning.py
autogonai/development/auto_machine_learning.py
autogonai/development/base.py
autogonai/development/data_processing.py
autogonai/development/deep_learning.py
autogonai/development/machine_learning.py
autogonai-0.2.1.dist-info/LICENSE
autogonai-0.2.1.dist-info/METADATA
autogonai-0.2.1.dist-info/WHEEL
autogonai-0.2.1.dist-info/top_level.txt
autogonai-0.2.1.dist-info/RECORD
