Metadata-Version: 2.1
Name: autogonai
Version: 0.2.1
Summary: Python connector for Autogon Public APIs
Home-page: https://github.com/autogoninc/autogonai-python
Author: David Mbatuegwu
Author-email: david@autogon.ai
Maintainer: Chiemezie Njoku
Maintainer-email: manuel@autogon.ai
License: UNKNOWN
Platform: UNKNOWN
Classifier: Development Status :: 4 - Beta
Classifier: Intended Audience :: Developers
Classifier: License :: OSI Approved :: MIT License
Classifier: Programming Language :: Python :: 3
Classifier: Programming Language :: Python :: 3.6
Classifier: Programming Language :: Python :: 3.7
Classifier: Programming Language :: Python :: 3.8
Classifier: Programming Language :: Python :: 3.9
Requires-Dist: python-dotenv (==1.0.0)
